dbcsv/__init__.py
dbcsv/app/__init__.py
dbcsv/app/dependencies.py
dbcsv/app/main.py
dbcsv/app/api/__init__.py
dbcsv/app/api/routes/__init__.py
dbcsv/app/api/routes/auth.py
dbcsv/app/api/routes/query.py
dbcsv/app/api/schemas/__init__.py
dbcsv/app/api/schemas/auth.py
dbcsv/app/api/schemas/sql_request.py
dbcsv/app/core/__init__.py
dbcsv/app/core/config.py
dbcsv/app/core/database_engine.py
dbcsv/app/core/dbapi2/__init__.py
dbcsv/app/core/dbapi2/connection.py
dbcsv/app/core/dbapi2/exception.py
dbcsv/app/core/dbapi2/utils.py
dbcsv/app/core/parser/__init__.py
dbcsv/app/core/parser/sql_parser.py
dbcsv/app/core/storage_layer/__init__.py
dbcsv/app/core/storage_layer/datatypes.py
dbcsv/app/core/storage_layer/executer.py
dbcsv/app/core/storage_layer/metadata.py
dbcsv/app/core/storage_layer/storage_test.py
dbcsv/app/core/storage_layer/sub_table.py
dbcsv/app/core/storage_layer/table.py
dbcsv/app/security/__init__.py
dbcsv/app/security/auth.py
dbcsv/scripts/test.py
dbcsv/tests/__init__.py
dbcsv/tests/unit/__init__.py
dbcsv/tests/unit/dbapi2/__init__.py
dbcsv/tests/unit/dbapi2/test_dbapi2.py
dbcsv/tests/unit/parser/__init__.py
dbcsv/tests/unit/parser/test_parser.py
dbcsv/tests/unit/security/__init__.py
dbcsv/tests/unit/security/test_auth.py
dbcsv-0.1.0.dist-info/METADATA
dbcsv-0.1.0.dist-info/WHEEL
dbcsv-0.1.0.dist-info/top_level.txt
dbcsv-0.1.0.dist-info/RECORD
